dshake/__init__.py
dshake/cli.py
dshake/data_model.py
dshake/dependency.py
dshake/module_import.py
dshake/package.py
dshake/utils.py
dshake-0.1.1.dist-info/licenses/LICENSE
dshake-0.1.1.dist-info/METADATA
dshake-0.1.1.dist-info/WHEEL
dshake-0.1.1.dist-info/entry_points.txt
dshake-0.1.1.dist-info/top_level.txt
dshake-0.1.1.dist-info/RECORD
