Metadata-Version: 2.4
Name: dshake
Version: 0.1.1
Summary: Dependency Shake: Analyze actual package usage in your Python codebase.
Author-email: Zhetao Dong <zhetao.dong@gmail.com>
License: MIT License
Project-URL: Homepage, https://github.com/donin1129/dependency-shaking
Classifier: License :: OSI Approved :: MIT License
Classifier: Programming Language :: Python
Classifier: Programming Language :: Python :: 3
Requires-Python: >=3.9
License-File: LICENSE
Provides-Extra: dev
Requires-Dist: pytest; extra == "dev"
Dynamic: license-file
